[
  {
    "title": "LoreRim",
    "description": "LoreRim is a modern action RPG modlist with a heavy emphasis on role-playing and making the lands of Skyrim feel alive. You\u0027ll encounter enemies and find gear seen in previous Elder Scrolls titles. Don\u0027t give up!",
    "author": "Biggie_Boss",
    "maintainers": [
      "github/biggie-boss",
      "github/silkilee93"
    ],
    "game": "skyrimspecialedition",
    "official": true,
    "tags": [
      "Official",
      "Anniversary Edition",
      "Requiem",
      "MCO"
    ],
    "nsfw": false,
    "utility_list": false,
    "image_contains_title": true,
    "DisplayVersionOnlyInInstallerView": false,
    "force_down": false,
    "links": {
      "image": "https://staticdelivery.nexusmods.com/mods/1704/images/112590/112590-1764892877-589382340.png",
      "readme": "https://lorerim.com/",
      "download": "https://authored-files.wabbajack.org/LoreRim.wabbajack_6b45aab2-6c2f-4a19-b679-94c88b83cf23",
      "machineURL": "LoreRim",
      "discordURL": "https://discord.gg/bungalo",
      "websiteURL": "https://lorerim.com/"
    },
    "download_metadata": {
      "Hash": "K81hqAe/BPI=",
      "Size": 4361187188,
      "NumberOfArchives": 4442,
      "SizeOfArchives": 258005823148,
      "NumberOfInstalledFiles": 424144,
      "SizeOfInstalledFiles": 343513480853,
      "TotalSize": 601519304001
    },
    "version": "4.4.3",
    "dateCreated": "1970-01-01T00:00:00Z",
    "dateUpdated": "2025-12-22T03:49:57.8173263Z",
    "repositoryName": ""
  }
]